Metadata-Version: 1.0
Name: pas
Version: 1.4.0
Summary: Secure password manager..
Home-page: UNKNOWN
Author: bindh3x
Author-email: <os@bindh3x.io>
License: UNKNOWN
Platform: UNKNOWN
